[{"_path":"/content","title":"Content","position":1},{"_path":"/pages","title":"Pages","position":2},{"_path":"/vue-files","title":"Vue Files","position":3},{"_path":"/routing","title":"Routing","position":4},{"_path":"/components","title":"Components","position":5},{"_path":"/network","title":"Network","position":6},{"_path":"/spa","title":"SPA","position":7},{"_path":"/configuration","title":"Configuration","position":8},{"_path":"/plugins","title":"Plugins","position":9},{"_path":"/setup-guide","title":"Setup Guide","position":100},{"_path":"/build-and-run","title":"Build & Run","position":101},{"_path":"/contributing","title":"Contributing","position":102},{"_path":"/migrations","title":"Migrations","position":103}]